dma_controller.v
//DMA Controller
module dma_controller (
    input clk,
    input reset,
    input start,
    input [7:0] src_addr_in,
    input [7:0] dst_addr_in,
    input [7:0] length_in,
    
    output reg done,
    output reg mem_we,             // write enable for memory
    output reg [7:0] mem_addr,     // address we are asking memory for
    output reg [7:0] mem_data_out, // data we are writing to memory
    input [7:0] mem_data_in        // data we are reading from memory
);

    // 3 states of fsm
localparam IDLE  = 2'b00;
    localparam READ  = 2'b01;
    localparam WRITE = 2'b10;
    localparam DONE  = 2'b11; //*

    reg [1:0] state;
    reg [7:0] src_reg, dst_reg, length_reg;
    reg [7:0] data_buffer; // temporarily holds moving data

    always @(posedge clk or posedge reset) begin
        if (reset) begin
            state <= IDLE;
            done <= 0;
            mem_we <= 0;

        end else begin
            case (state)
                IDLE: begin
                    done <= 0;
                    mem_we <= 0;
                    if (start) begin
                        src_reg <= src_addr_in;
                        dst_reg <= dst_addr_in;
                        length_reg <= length_in;
                        state <= READ;
                    end
                end

                READ: begin
                    mem_we <= 0;
                    mem_addr <= src_reg; // ask memory for source data
                    state <= WRITE;
                end

                WRITE: begin
                    mem_we <= 1; // tell memory we are writing
                    mem_addr <= dst_reg;
                    mem_data_out <= mem_data_in; // pass the read data to the output
                    
                    // update our counters for the next loop
                    src_reg <= src_reg + 1;
                    dst_reg <= dst_reg + 1;
                    length_reg <= length_reg - 1;

                    if (length_reg == 1) begin
                        state <= DONE; // * previously we moved the last byte and moved to IDLE now we move to DONE
                    end else begin
                        state <= READ; // keep looping onto next loop
                    end
                end
                DONE: begin
                    mem_we <= 0; // turn off write signal to prevent overwrite
                    done <= 1;   // tell the CPU we are properly! finished
                    state <= IDLE;
                end
            endcase
        end
    end
endmodule

dma_controller_tb.v
// DMA Controller - testbench
module testbench;
    reg clk, reset, start;
    reg [7:0] src, dst, len;
    wire done, mem_we;
    wire [7:0] mem_addr, mem_data_out;
    wire [7:0] mem_data_in;

    //  a fake SRAM memory-(256 bytes)
    reg [7:0] sram [0:255]; 

    // create DMA Controller
    dma_controller dma (
        .clk(clk), .reset(reset), .start(start),
        .src_addr_in(src), .dst_addr_in(dst), .length_in(len),
        .done(done), .mem_we(mem_we), .mem_addr(mem_addr),
        .mem_data_out(mem_data_out), .mem_data_in(mem_data_in)
    );

    
    always #5 clk = ~clk;// clock signal - 5 nanoseconds

    //////// fake memory logic ////////////
    always @(posedge clk) begin
        if (mem_we) sram[mem_addr] <= mem_data_out; // write
    end
    assign mem_data_in = sram[mem_addr];            // asynchronous Read

    // main execution
    initial begin
        $dumpfile("dump.vcd");
        $dumpvars(0, testbench);
        
        clk = 0; reset = 1; start = 0;
        // doad fake data into memory
        sram[10] = 8'hAA; // Hex value AA at address 10
        sram[11] = 8'hBB; // Hex value BB at address 11
        sram[12] = 8'hCC; // Hex value CC at address 12
        
        #10 reset = 0; // turn off reset

        //CPU commands DMA to move 3 bytes from Addr 10 to Addr 50
        $display("--- STARTING DMA TRANSFER ---");
        src = 10; dst = 50; len = 3;
        start = 1; #10 start = 0; // start button

        // wait for DMA to finish
        wait(done == 1);
        #10;
        
        //final reults displayed
        $display("--- TRANSFER COMPLETE ---");
        $display("Memory Addr 50: %h (Expected AA)", sram[50]);
        $display("Memory Addr 51: %h (Expected BB)", sram[51]);
        $display("Memory Addr 52: %h (Expected CC)", sram[52]);
        
        $finish;
    end
endmodule

dump.vcd
$date
	Fri Mar 27 17:11:08 2026
$end
$version
	Icarus Verilog
$end
$timescale
	1s
$end
$scope module testbench $end
$var wire 8 ! mem_data_in [7:0] $end
$var wire 1 " mem_we $end
$var wire 8 # mem_data_out [7:0] $end
$var wire 8 $ mem_addr [7:0] $end
$var wire 1 % done $end
$var reg 1 & clk $end
$var reg 8 ' dst [7:0] $end
$var reg 8 ( len [7:0] $end
$var reg 1 ) reset $end
$var reg 8 * src [7:0] $end
$var reg 1 + start $end
$scope module dma $end
$var wire 1 & clk $end
$var wire 8 , dst_addr_in [7:0] $end
$var wire 8 - length_in [7:0] $end
$var wire 8 . mem_data_in [7:0] $end
$var wire 1 ) reset $end
$var wire 8 / src_addr_in [7:0] $end
$var wire 1 + start $end
$var parameter 2 0 DONE $end
$var parameter 2 1 IDLE $end
$var parameter 2 2 READ $end
$var parameter 2 3 WRITE $end
$var reg 1 % done $end
$var reg 8 4 dst_reg [7:0] $end
$var reg 8 5 length_reg [7:0] $end
$var reg 8 6 mem_addr [7:0] $end
$var reg 8 7 mem_data_out [7:0] $end
$var reg 1 " mem_we $end
$var reg 8 8 src_reg [7:0] $end
$var reg 2 9 state [1:0] $end
$upscope $end
$upscope $end
$enddefinitions $end
$comment Show the parameter values. $end
$dumpall
b10 3
b1 2
b0 1
b11 0
$end
#0
$dumpvars
b0 9
bx 8
bx 7
bx 6
bx 5
bx 4
bx /
bx .
bx -
bx ,
0+
bx *
1)
bx (
bx '
0&
0%
bx $
bx #
0"
bx !
$end
#5
1&
#10
0&
1+
b11 (
b11 -
b110010 '
b110010 ,
b1010 *
b1010 /
0)
#15
b1 9
b11 5
b110010 4
b1010 8
1&
#20
0&
0+
#25
b10101010 !
b10101010 .
b10 9
b1010 $
b1010 6
1&
#30
0&
#35
bx !
bx .
b1 9
b10 5
b110011 4
b1011 8
b10101010 #
b10101010 7
b110010 $
b110010 6
1"
1&
#40
0&
#45
b10 9
b1011 $
b1011 6
0"
b10111011 !
b10111011 .
1&
#50
0&
#55
bx !
bx .
b1 9
b1 5
b110100 4
b1100 8
b10111011 #
b10111011 7
b110011 $
b110011 6
1"
1&
#60
0&
#65
b10 9
b1100 $
b1100 6
0"
b11001100 !
b11001100 .
1&
#70
0&
#75
bx !
bx .
b11 9
b0 5
b110101 4
b1101 8
b11001100 #
b11001100 7
b110100 $
b110100 6
1"
1&
#80
0&
#85
b0 9
1%
0"
b11001100 !
b11001100 .
1&
#90
0&
#95
0%
1&
